pysqlcipher3/_sqlite3.cpython-311-darwin.so
pysqlcipher3/__init__.py
pysqlcipher3/dump.py
pysqlcipher3/dbapi2.py
pysqlcipher3/test/__init__.py
pysqlcipher3/test/python3/hooks.py
pysqlcipher3/test/python3/regression.py
pysqlcipher3/test/python3/dbapi.py
pysqlcipher3/test/python3/transactions.py
pysqlcipher3/test/python3/__init__.py
pysqlcipher3/test/python3/types.py
pysqlcipher3/test/python3/factory.py
pysqlcipher3/test/python3/dump.py
pysqlcipher3/test/python3/userfunctions.py
pysqlcipher3/test/python3/sqlcipher.py
rotki_pysqlcipher3-2024.10.1.dist-info/RECORD
rotki_pysqlcipher3-2024.10.1.dist-info/LICENSE
rotki_pysqlcipher3-2024.10.1.dist-info/WHEEL
rotki_pysqlcipher3-2024.10.1.dist-info/top_level.txt
rotki_pysqlcipher3-2024.10.1.dist-info/METADATA
