Metadata-Version: 2.1
Name: rotki-pysqlcipher3
Version: 2024.10.1
Summary: DB-API 2.0 interface for SQLCIPHER 4.x
Home-page: https://github.com/rotki/pysqlcipher3
Author: Rotki Solutions GmbH
Author-email: info@rotki.com
License: zlib/libpng
Platform: ALL
Classifier: Development Status :: 4 - Beta
Classifier: Intended Audience :: Developers
Classifier: License :: OSI Approved :: zlib/libpng License
Classifier: Operating System :: MacOS :: MacOS X
Classifier: Operating System :: Microsoft :: Windows
Classifier: Operating System :: POSIX
Classifier: Programming Language :: C
Classifier: Programming Language :: Python
Classifier: Topic :: Database :: Database Engines/Servers
Classifier: Topic :: Software Development :: Libraries :: Python Modules
Requires-Python: >=3.3
License-File: LICENSE
